mack_SDK/__init__.py
mack_SDK/client.py
mack_SDK/resources/__init__.py
mack_SDK/resources/models.py
mack_SDK/resources/movie.py
mack_SDK/resources/quote.py
mack_SDK/tools/__init__.py
mack_SDK/tools/raise_for_status.py
mack_SDK/tools/settings.py
mack_sdk-0.1.9.dist-info/METADATA
mack_sdk-0.1.9.dist-info/WHEEL
mack_sdk-0.1.9.dist-info/RECORD
