Metadata-Version: 2.1
Name: mack-sdk
Version: 0.1.9
Summary: LOTR SDK
Author: Maksym Iv
Author-email: maxim.ivaschenko@gmail.com
Requires-Python: >=3.11,<3.12
Classifier: Programming Language :: Python :: 3
Classifier: Programming Language :: Python :: 3.11
Requires-Dist: httpx (>=0.24.1,<0.25.0)
Requires-Dist: pydantic (>=1.10.8,<2.0.0)
Requires-Dist: python-dateutil (>=2.8.2,<3.0.0)
